bin/__init__.py
bin/read.py
bin/viewer.py
edam/__init__.py
edam/reader/__init__.py
edam/reader/base.py
edam/reader/database_handler.py
edam/reader/regular_expressions.py
edam/reader/models/__init__.py
edam/reader/models/app.py
edam/reader/models/database.py
edam/reader/models/junction.py
edam/reader/models/measurement.py
edam/reader/models/metadata.py
edam/reader/models/observable.py
edam/reader/models/observation.py
edam/reader/models/sensor.py
edam/reader/models/station.py
edam/reader/models/template.py
edam/reader/models/unit_of_measurement.py
edam/reader/models/utilities.py
edam/reader/resolvers/__init__.py
edam/reader/resolvers/file_resolver.py
edam/reader/resolvers/http_resolver.py
edam/reader/resolvers/resolver.py
edam/reader/resolvers/resolver_factory.py
edam/reader/resolvers/resolver_utilities.py
edam/resources/edam.owl
edam/resources/settings.yaml
edam/resources/flask_related/static/jquery.flot.js
edam/resources/flask_related/static/bootstrap/css/bootstrap-theme.css
edam/resources/flask_related/static/bootstrap/css/bootstrap-theme.min.css
edam/resources/flask_related/static/bootstrap/css/bootstrap.css
edam/resources/flask_related/static/bootstrap/css/bootstrap.min.css
edam/resources/flask_related/static/bootstrap/fonts/glyphicons-halflings-regular.eot
edam/resources/flask_related/static/bootstrap/fonts/glyphicons-halflings-regular.svg
edam/resources/flask_related/static/bootstrap/fonts/glyphicons-halflings-regular.ttf
edam/resources/flask_related/static/bootstrap/fonts/glyphicons-halflings-regular.woff
edam/resources/flask_related/static/bootstrap/js/bootstrap.js
edam/resources/flask_related/static/bootstrap/js/bootstrap.min.js
edam/resources/flask_related/static/css/app.css
edam/resources/flask_related/static/css/bootstrap-grid.css
edam/resources/flask_related/static/css/bootstrap-grid.css.map
edam/resources/flask_related/static/css/bootstrap-grid.min.css
edam/resources/flask_related/static/css/bootstrap-grid.min.css.map
edam-2.0.3.dist-info/LICENSE
edam-2.0.3.dist-info/METADATA
edam-2.0.3.dist-info/WHEEL
edam-2.0.3.dist-info/entry_points.txt
edam-2.0.3.dist-info/top_level.txt
edam-2.0.3.dist-info/RECORD
