Metadata-Version: 2.1
Name: edam
Version: 2.0.3
Summary: An input template framework
Home-page: https://github.com/BigDataWUR/EDAM
Author: Argyrios Samourkasidis
Author-email: argysamo@gmail.com
License: GNU General Public License v3.0
Platform: UNKNOWN
Classifier: Programming Language :: Python :: 3
Classifier: Programming Language :: Python :: 3.7
Classifier: Programming Language :: Python :: 3.8
Classifier: Programming Language :: Python :: 3.9
Classifier: Programming Language :: Python :: 3.10
Requires-Python: >=3.7
License-File: LICENSE
Requires-Dist: PyYAML (==6.0)
Requires-Dist: SQLAlchemy (==1.4.36)
Requires-Dist: requests (==2.27.1)
Requires-Dist: numpy (==1.21.6)
Requires-Dist: pandas (==1.3.5)
Requires-Dist: Flask (==2.1.2)
Requires-Dist: Flask-SQLAlchemy (==2.5.1)
Requires-Dist: Jinja2 (==3.1.2)
Requires-Dist: geopy (==2.2.0)
Requires-Dist: records (==0.5.3)
Requires-Dist: click (==8.1.3)
Requires-Dist: flask-googlemaps (==0.2.4)
Requires-Dist: detect-delimiter (==0.1.1)
Requires-Dist: jinja2schema (==0.1.4)
Requires-Dist: plotly (==5.8.0)
